logging_/__init__.py
logging_/version.py
logging_/config/__init__.py
logging_/config/yaml_config.py
logging_/handlers/__init__.py
logging_/handlers/queue_listener_handler.py
tests/test_config/__init__.py
tests/test_config/test_yaml_config.py
tests/test_handlers/__init__.py
tests/test_handlers/test_queue_listener_handler.py
logging_extras-0.3.0b0.dist-info/LICENSE
logging_extras-0.3.0b0.dist-info/METADATA
logging_extras-0.3.0b0.dist-info/WHEEL
logging_extras-0.3.0b0.dist-info/top_level.txt
logging_extras-0.3.0b0.dist-info/RECORD
